fhir_client/__init__.py
fhir_client/client.py
fhir_server_client-0.0.1.dist-info/licenses/LICENSE
fhir_server_client-0.0.1.dist-info/METADATA
fhir_server_client-0.0.1.dist-info/WHEEL
fhir_server_client-0.0.1.dist-info/top_level.txt
fhir_server_client-0.0.1.dist-info/RECORD
