Metadata-Version: 2.4
Name: fhir-server-client
Version: 0.0.1
Summary: A Python client for FHIR servers
Home-page: https://github.com/TobiKuehn7/fhir-client
Classifier: Programming Language :: Python :: 3
Classifier: License :: OSI Approved :: MIT License
Classifier: Operating System :: OS Independent
Requires-Python: >=3.6
License-File: LICENSE
Requires-Dist: requests>=2.32.5
Requires-Dist: setuptools>=80.9.0
Dynamic: classifier
Dynamic: description
Dynamic: description-content-type
Dynamic: home-page
Dynamic: license-file
Dynamic: requires-dist
Dynamic: requires-python
Dynamic: summary
